README.txt
setup.py
src/rebecca/__init__.py
src/rebecca.form.egg-info/PKG-INFO
src/rebecca.form.egg-info/SOURCES.txt
src/rebecca.form.egg-info/dependency_links.txt
src/rebecca.form.egg-info/entry_points.txt
src/rebecca.form.egg-info/namespace_packages.txt
src/rebecca.form.egg-info/not-zip-safe
src/rebecca.form.egg-info/requires.txt
src/rebecca.form.egg-info/top_level.txt
src/rebecca/form/__init__.py
src/rebecca/form/helpers.py
src/rebecca/form/tests.py
src/rebecca/form/utils.py
src/rebecca/form/views.py