Metadata-Version: 1.1
Name: rebecca.form
Version: 0.1
Summary: pyramid view components based on formalchemy
Home-page: https://github.com/rebeccaframework/rebecca.form
Author: Atsushi Odagiri
Author-email: aodagx@gmail.com
License: MIT
Platform: UNKNOWN
Classifier: Development Status :: 3 - Alpha
Classifier: Framework :: Pyramid
Classifier: Topic :: Internet :: WWW/HTTP :: WSGI
Classifier: Topic :: Software Development :: Libraries :: Python Modules
Classifier: Programming Language :: Python
